stackit/__init__.py
stackit/controls.py
stackit/core.py
stackit/delegate.py
stackit/sfsymbol.py
stackit/utils.py
stackitui-0.2.5.dist-info/licenses/LICENSE
stackitui-0.2.5.dist-info/METADATA
stackitui-0.2.5.dist-info/WHEEL
stackitui-0.2.5.dist-info/top_level.txt
stackitui-0.2.5.dist-info/RECORD
